{"content":[{"id":"blog-post-loop","heading":{"short":"Latest & Featured Blogs","medium":"Explore Our Latest and Featured Blog Posts"},"sentence":{"medium":"Stay updated with insights into career development and professional growth."},"overline":{"short":"Read Our Insights"},"button":{"short":"View All Posts"}},{"id":"blog-table-contents","heading":{"medium":"Empowering Your Career with Nanthini's Insights"},"overline":{"short":"Career Development Strategies"},"button":{"short":"Read More"},"subtitles":[{"title-short":"Skill Enhancement Techniques"},{"title-short":"Networking Opportunities Uncovered"},{"title-short":"Workshops for Professional Growth"},{"title-short":"Proactive Career Management Tips"}]}]}